geostat/__init__.py
geostat/custom_op.py
geostat/kernel.py
geostat/krige.py
geostat/mean.py
geostat/mesh.py
geostat/metric.py
geostat/model.py
geostat/op.py
geostat/param.py
geostat-0.11.3.dist-info/LICENSE
geostat-0.11.3.dist-info/METADATA
geostat-0.11.3.dist-info/WHEEL
geostat-0.11.3.dist-info/top_level.txt
geostat-0.11.3.dist-info/RECORD
