Metadata-Version: 2.2
Name: geostat
Version: 0.11.3
Summary: Model spatial data with Gaussian processes
Author-email: Will Chang <will@hypergradient.ai>
License:                                  Apache License
Project-URL: Homepage, https://github.com/whdc/geostat
Keywords: geospatial,spatial,interpolation,gaussian process,krige,kriging
Classifier: License :: OSI Approved :: Apache Software License
Classifier: Programming Language :: Python :: 3
Requires-Python: >=3.10
License-File: LICENSE
Requires-Dist: matplotlib>=3.0
Requires-Dist: numpy>=1.19
Requires-Dist: pandas>=1.2
Requires-Dist: scipy>=1.5
Requires-Dist: shapely>=1.8
Requires-Dist: tensorflow>=2.14
Requires-Dist: tensorflow_probability>=0.22.1
Requires-Dist: tf-keras>=2.18.0
Provides-Extra: extras
Requires-Dist: pytest>=3.0; extra == "extras"
Requires-Dist: pyproj>=3.0; extra == "extras"
